lazytables.py
lazytables-0.0.2.dist-info/METADATA
lazytables-0.0.2.dist-info/WHEEL
lazytables-0.0.2.dist-info/licenses/LICENSE
lazytables-0.0.2.dist-info/RECORD
