Metadata-Version: 2.1
Name: lazytables
Version: 0.0.2
Summary: A micro-framework for managing data sources.
Author-email: Ryan Young <dev@ryayoung.com>
License-Expression: MIT
License-File: LICENSE
Classifier: Development Status :: 3 - Alpha
Classifier: Intended Audience :: Developers
Classifier: License :: OSI Approved :: MIT License
Classifier: Operating System :: OS Independent
Classifier: Programming Language :: Python :: 3.11
Classifier: Topic :: Software Development :: Libraries
